heartstring1/__init__.py
heartstring1/add.py
heartstring1-1.0.0.dist-info/METADATA
heartstring1-1.0.0.dist-info/WHEEL
heartstring1-1.0.0.dist-info/top_level.txt
heartstring1-1.0.0.dist-info/RECORD
