Metadata-Version: 2.1
Name: heartstring1
Version: 1.0.0
Summary: this is a test model for pypi
Author: 
Author-email: 
License: UNKNOWN
Keywords: python,image processing
Platform: UNKNOWN
Classifier: Development Status :: 3 - Alpha
Classifier: Intended Audience :: Developers
Classifier: Intended Audience :: Science/Research
Classifier: Programming Language :: Python :: 3
Classifier: Operating System :: Unix
Classifier: Operating System :: MacOS :: MacOS X
Classifier: Operating System :: Microsoft :: Windows
